lektor_groupby/__init__.py
lektor_groupby/backref.py
lektor_groupby/config.py
lektor_groupby/groupby.py
lektor_groupby/model.py
lektor_groupby/pagination.py
lektor_groupby/plugin.py
lektor_groupby/pruner.py
lektor_groupby/query.py
lektor_groupby/resolver.py
lektor_groupby/util.py
lektor_groupby/vobj.py
lektor_groupby/watcher.py
lektor_groupby-1.0.0.dist-info/LICENSE
lektor_groupby-1.0.0.dist-info/METADATA
lektor_groupby-1.0.0.dist-info/WHEEL
lektor_groupby-1.0.0.dist-info/entry_points.txt
lektor_groupby-1.0.0.dist-info/top_level.txt
lektor_groupby-1.0.0.dist-info/RECORD
