Metadata-Version: 2.1
Name: lektor-groupby
Version: 1.0.0
Summary: Cluster arbitrary records with field attribute keyword.
Home-page: https://github.com/relikd/lektor-groupby-plugin
Author: relikd
License: MIT
Keywords: lektor,plugin,groupby,grouping,cluster
Platform: UNKNOWN
Classifier: Environment :: Web Environment
Classifier: Environment :: Plugins
Classifier: Framework :: Lektor
Classifier: License :: OSI Approved :: MIT License
Classifier: Operating System :: OS Independent
Classifier: Programming Language :: Python
Classifier: Programming Language :: Python :: 3
Classifier: Programming Language :: Python :: 3 :: Only
Classifier: Programming Language :: Python :: 3.6
Classifier: Programming Language :: Python :: 3.7
Classifier: Programming Language :: Python :: 3.8
Requires-Python: >=3.6
